{
  "feature_version": "v1_fix3",
  "created_at": "2026-04-23T01:16:45.103389",
  "features": [
    "video_id",
    "page_url",
    "author_id",
    "publish_time_raw",
    "crawl_time",
    "author_follower_count",
    "author_total_favorited",
    "hashtag_count",
    "duration_sec",
    "collect_count",
    "like_count_num",
    "comment_count_num",
    "share_count_num",
    "publish_hour",
    "publish_weekday",
    "is_weekend",
    "days_since_publish",
    "source_entry",
    "match_type",
    "confidence",
    "author_verification_type",
    "desc_text",
    "author_name",
    "hashtag_list",
    "desc_text_length",
    "has_desc_text",
    "has_hashtag"
  ],
  "dtypes": {
    "video_id": "string",
    "page_url": "object",
    "author_id": "object",
    "publish_time_raw": "object",
    "crawl_time": "datetime64[ns]",
    "author_follower_count": "int32",
    "author_total_favorited": "int32",
    "hashtag_count": "int32",
    "duration_sec": "int32",
    "collect_count": "int32",
    "like_count_num": "int64",
    "comment_count_num": "int64",
    "share_count_num": "int64",
    "publish_hour": "int32",
    "publish_weekday": "int32",
    "is_weekend": "int32",
    "days_since_publish": "int32",
    "source_entry": "object",
    "match_type": "object",
    "confidence": "object",
    "author_verification_type": "object",
    "desc_text": "object",
    "author_name": "object",
    "hashtag_list": "object",
    "desc_text_length": "int64",
    "has_desc_text": "int32",
    "has_hashtag": "int32"
  }
}